sshkernel/__init__.py
sshkernel/__main__.py
sshkernel/exception.py
sshkernel/kernel.py
sshkernel/ssh_wrapper.py
sshkernel/ssh_wrapper_plumbum.py
sshkernel/version.py
sshkernel/magics/magics.py
sshkernel-0.11.1.dist-info/LICENSE
sshkernel-0.11.1.dist-info/METADATA
sshkernel-0.11.1.dist-info/WHEEL
sshkernel-0.11.1.dist-info/top_level.txt
sshkernel-0.11.1.dist-info/RECORD
