Metadata-Version: 2.1
Name: sshkernel
Version: 0.11.1
Summary: SSH Kernel
Home-page: https://github.com/nii-cloud-operation/sshkernel
Author: UENO, Masaru
Author-email: ueno.masaru@fujitsu.com
License: BSD 3-clause "New" or "Revised License"
Platform: any
Classifier: Framework :: IPython
Classifier: Framework :: Jupyter
Classifier: License :: OSI Approved :: BSD License
Classifier: Operating System :: OS Independent
Classifier: Programming Language :: Python :: 3
Classifier: Topic :: System :: Shells
License-File: LICENSE
Requires-Dist: ipykernel (>=5.0.0)
Requires-Dist: ipython (>=7.0.0)
Requires-Dist: jupyter-client (>=5.2.0)
Requires-Dist: metakernel (>=0.20.0)
Requires-Dist: nbconvert (>=5.4.1)
Requires-Dist: paramiko (>=2.4.2)
Requires-Dist: plumbum
Requires-Dist: PyYAML
Provides-Extra: dev
Requires-Dist: pytest (>=3) ; extra == 'dev'
Requires-Dist: pytest-watch ; extra == 'dev'
